README
setup.py
WSGI_middleware/__init__.py
WSGI_middleware.egg-info/PKG-INFO
WSGI_middleware.egg-info/SOURCES.txt
WSGI_middleware.egg-info/dependency_links.txt
WSGI_middleware.egg-info/top_level.txt