Metadata-Version: 1.0
Name: WSGI-middleware
Version: 0.0.100
Summary: Usage of WSGI middleware
Home-page: UNKNOWN
Author: John Mutuma
Author-email: johnmutuma5@gmail.com
License: None
Platform: UNKNOWN
